Metadata-Version: 2.1
Name: HashGenerator
Version: 1.0.1
Summary: A simple file hash calculator supporting multiple algorithms
Home-page: https://github.com/LpCodes/HashGenerator
Author: LpCodes
Keywords: file,hash,hashing,checksum,algorithm,md5,sha1,sha256,sha512
Classifier: Programming Language :: Python :: 3
Classifier: License :: OSI Approved :: MIT License
Classifier: Operating System :: OS Independent
Requires-Python: >=3.6
